xpectrass/__init__.py
xpectrass/main.py
xpectrass/data/__init__.py
xpectrass/data/frond_2021.csv.xz
xpectrass/data/jung_2018.csv.xz
xpectrass/data/kedzierski_2019.csv.xz
xpectrass/data/kedzierski_2019_u.csv.xz
xpectrass/data/villegas_camacho_2024_c4.csv.xz
xpectrass/data/villegas_camacho_2024_c8.csv.xz
xpectrass/utils/__init__.py
xpectrass/utils/atmospheric.py
xpectrass/utils/baseline.py
xpectrass/utils/data_validation.py
xpectrass/utils/denoise.py
xpectrass/utils/derivatives.py
xpectrass/utils/file_management.py
xpectrass/utils/interpolate.py
xpectrass/utils/ml.py
xpectrass/utils/normalization.py
xpectrass/utils/normalization_eval.py
xpectrass/utils/plotting.py
xpectrass/utils/plotting_clus.py
xpectrass/utils/plotting_dim.py
xpectrass/utils/plotting_stats.py
xpectrass/utils/plottingx.py
xpectrass/utils/region_selection.py
xpectrass/utils/scatter_correction.py
xpectrass/utils/spectral_utils.py
xpectrass/utils/trans_abs.py
xpectrass/utils/warnings.py
xpectrass-0.0.3.dist-info/licenses/LICENSE
xpectrass-0.0.3.dist-info/METADATA
xpectrass-0.0.3.dist-info/WHEEL
xpectrass-0.0.3.dist-info/top_level.txt
xpectrass-0.0.3.dist-info/RECORD
