Metadata-Version: 2.4
Name: xpectrass
Version: 0.0.3
Summary: FTIR/ToF-SIMS Spectral Analysis Suite - Preprocessing toolkit for spectral classification
Home-page: https://github.com/kazilab/xpectrass
Author: Data Analysis Team @KaziLab.se
Author-email: "Data Analysis Team @KaziLab.se" <xpectrass@kazilab.se>
Maintainer-email: "Data Analysis Team @KaziLab.se" <xpectrass@kazilab.se>
License: MIT
Project-URL: Homepage, https://github.com/kazilab/xpectrass
Project-URL: Documentation, https://xpectrass.readthedocs.io/
Project-URL: Repository, https://github.com/kazilab/xpectrass
Project-URL: Issues, https://github.com/kazilab/xpectrass/issues
Project-URL: Changelog, https://github.com/kazilab/xpectrass/blob/main/CHANGELOG.md
Keywords: FTIR,spectroscopy,preprocessing,baseline correction,plastic classification,ToF-SIMS,chemometrics,machine learning
Classifier: Development Status :: 4 - Beta
Classifier: Intended Audience :: Science/Research
Classifier: Intended Audience :: Developers
Classifier: License :: OSI Approved :: MIT License
Classifier: Operating System :: OS Independent
Classifier: Programming Language :: Python :: 3
Classifier: Programming Language :: Python :: 3.8
Classifier: Programming Language :: Python :: 3.9
Classifier: Programming Language :: Python :: 3.10
Classifier: Programming Language :: Python :: 3.11
Classifier: Programming Language :: Python :: 3.12
Classifier: Topic :: Scientific/Engineering :: Chemistry
Classifier: Topic :: Scientific/Engineering :: Physics
Classifier: Typing :: Typed
Requires-Python: >=3.8
License-File: LICENSE
Requires-Dist: numpy==2.3.5
Requires-Dist: scipy==1.16.3
Requires-Dist: pandas==2.3.3
Requires-Dist: polars==1.37.0
Requires-Dist: pybaselines==1.2.1
Requires-Dist: PyWavelets==1.9.0
Requires-Dist: matplotlib==3.10.8
Requires-Dist: seaborn==0.13.2
Requires-Dist: plotly==6.5.1
Requires-Dist: scikit-learn==1.8.0
Requires-Dist: xgboost==3.1.3
Requires-Dist: lightgbm==4.6.0
Requires-Dist: umap-learn==0.5.9.post2
Requires-Dist: shap==0.50.0
Requires-Dist: tqdm==4.67.1
Requires-Dist: joblib==1.5.3
Requires-Dist: cloudpickle==3.1.2
Requires-Dist: contourpy==1.3.3
Requires-Dist: cycler==0.12.1
Requires-Dist: et-xmlfile==2.0.0
Requires-Dist: fonttools==4.61.1
Requires-Dist: graphviz==0.21
Requires-Dist: kiwisolver==1.4.9
Requires-Dist: llvmlite==0.46.0
Requires-Dist: narwhals==2.15.0
Requires-Dist: numba==0.63.1
Requires-Dist: pillow==12.1.0
Requires-Dist: polars-runtime-32==1.37.0
Requires-Dist: pynndescent==0.6.0
Requires-Dist: pyparsing==3.3.1
Requires-Dist: pytz==2025.2
Requires-Dist: openpyxl==3.1.5
Requires-Dist: slicer==0.0.8
Requires-Dist: threadpoolctl==3.6.0
Requires-Dist: typing-extensions==4.15.0
Requires-Dist: tzdata==2025.3
Provides-Extra: dev
Requires-Dist: pytest>=7.0.0; extra == "dev"
Requires-Dist: pytest-cov>=3.0.0; extra == "dev"
Requires-Dist: black>=22.0.0; extra == "dev"
Requires-Dist: isort>=5.10.0; extra == "dev"
Requires-Dist: flake8>=4.0.0; extra == "dev"
Requires-Dist: mypy>=0.950; extra == "dev"
Requires-Dist: pre-commit>=2.17.0; extra == "dev"
Provides-Extra: docs
Requires-Dist: sphinx>=4.0.0; extra == "docs"
Requires-Dist: sphinx-rtd-theme>=1.0.0; extra == "docs"
Requires-Dist: myst-parser>=0.18.0; extra == "docs"
Requires-Dist: sphinx-autodoc-typehints>=1.18.0; extra == "docs"
Dynamic: author
Dynamic: home-page
Dynamic: license-file
Dynamic: requires-python
